Morse/__init__.py
Morse/morse.py
Morse_ruxia_TJY-0.0.1.dist-info/LICENSE
Morse_ruxia_TJY-0.0.1.dist-info/METADATA
Morse_ruxia_TJY-0.0.1.dist-info/WHEEL
Morse_ruxia_TJY-0.0.1.dist-info/top_level.txt
Morse_ruxia_TJY-0.0.1.dist-info/RECORD
