Metadata-Version: 2.1
Name: Morse-ruxia-TJY
Version: 0.0.1
Summary: Morse encode/decode
Home-page: https://github.com/ruxia-TJY/Morse
Author: ruxia-TJY
Author-email: ruxia.tjy@qq.com
License: BSD 3-Clause
Download-URL: https://github.com/ruxia-TJY/Morse
Project-URL: Bug Tracker, https://github.com/ruxia-TJY/Morse/issues
Keywords: Morse encode decode
Platform: UNKNOWN
Classifier: Programming Language :: Python :: 3
Classifier: Operating System :: MacOS
Classifier: Operating System :: POSIX :: Linux
Classifier: Operating System :: Microsoft :: Windows
Classifier: License :: OSI Approved :: BSD License
Requires-Python: >=3
